{
    "status": "OK",
    "data-availability": "available",
    "last_update": "2025-02-27 04:14:34",
    "subject": [
        {
            "val": 531,
            "label": "Neraca Ekonomi"
        }
    ],
    "var": [
        {
            "val": 161,
            "label": "PDRB Atas Dasar Harga Berlaku Menurut Jenis Pengeluaran di Kabupaten Samosir",
            "unit": "Milyar Rupiah",
            "subj": "Produk Domestik Regional Bruto Menurut Pengeluaran",
            "def": "Distribusi PDRB harga berlaku menurut lapangan usaha menunjukkan struktur perekonomian atau peranan setiap kategori ekonomi dalam suatu wilayah. Kategori-kategori ekonomi yang mempunyai peran besar menunjukkan basis perekonomian suatu wilayah.",
            "decimal": 2,
            "note": " * Angka Sementara (2023)\n** Angka Sangat Sementara (2024)"
        }
    ],
    "turvar": [
        {
            "val": "0",
            "label": "Tidak ada"
        }
    ],
    "labelvervar": "Komponen PDRB Pengeluaran",
    "vervar": [
        {
            "val": 1,
            "label": "1. Pengeluaran Konsumsi Rumahtangga"
        },
        {
            "val": 2,
            "label": "2. Pengeluaran Konsumsi LNPRT"
        },
        {
            "val": 3,
            "label": "3. Pengeluaran Konsumsi Pemerintah"
        },
        {
            "val": 4,
            "label": "4. Pembentukan Modal Tetap Bruto"
        },
        {
            "val": 5,
            "label": "5. Perubahan Inventori"
        },
        {
            "val": 6,
            "label": "6. Net Ekspor Barang dan Jasa"
        },
        {
            "val": 7,
            "label": "PRODUK DOMESTIK REGIONAL BRUTO"
        }
    ],
    "tahun": [
        {
            "val": 110,
            "label": "2010"
        },
        {
            "val": 111,
            "label": "2011"
        },
        {
            "val": 112,
            "label": "2012"
        },
        {
            "val": 113,
            "label": "2013"
        },
        {
            "val": 114,
            "label": "2014"
        },
        {
            "val": 115,
            "label": "2015"
        },
        {
            "val": 116,
            "label": "2016"
        },
        {
            "val": 117,
            "label": "2017"
        },
        {
            "val": 118,
            "label": "2018"
        },
        {
            "val": 119,
            "label": "2019"
        },
        {
            "val": 120,
            "label": "2020"
        },
        {
            "val": 121,
            "label": "2021"
        },
        {
            "val": 122,
            "label": "2022"
        },
        {
            "val": 123,
            "label": "2023"
        },
        {
            "val": 124,
            "label": "2024"
        }
    ],
    "turtahun": [
        {
            "val": 0,
            "label": "Tahun"
        }
    ],
    "datacontent": {
        "116101100": 1063.31,
        "116101110": 1183.12,
        "116101120": 1310.09,
        "116101130": 1464.2,
        "116101140": 1640.04,
        "116101150": 1852.97,
        "116101160": 2038.2,
        "116101170": 2237.3,
        "116101180": 2427.91,
        "116101190": 2651.8,
        "116101200": 2668.77,
        "116101210": 2793.23,
        "116101220": 3096.12,
        "116101230": 3461.18,
        "116101240": 3719.16,
        "216101100": 43.21,
        "216101110": 48.55,
        "216101120": 52.43,
        "216101130": 58.43,
        "216101140": 66.51,
        "216101150": 72.16,
        "216101160": 79.29,
        "216101170": 84.02,
        "216101180": 93.54,
        "216101190": 104.82,
        "216101200": 108.95,
        "216101210": 112.71,
        "216101220": 122.09,
        "216101230": 134.32,
        "216101240": 150.06,
        "316101100": 458.18,
        "316101110": 530.32,
        "316101120": 580.57,
        "316101130": 619.67,
        "316101140": 682.09,
        "316101150": 760.91,
        "316101160": 807.85,
        "316101170": 880.71,
        "316101180": 950.3,
        "316101190": 974.09,
        "316101200": 978.45,
        "316101210": 1010.98,
        "316101220": 1021.34,
        "316101230": 1066.55,
        "316101240": 1102.37,
        "416101100": 279.96,
        "416101110": 303.81,
        "416101120": 340.67,
        "416101130": 388.63,
        "416101140": 452.07,
        "416101150": 479.1,
        "416101160": 506.07,
        "416101170": 539.35,
        "416101180": 591.99,
        "416101190": 635.03,
        "416101200": 630.47,
        "416101210": 684.48,
        "416101220": 750.01,
        "416101230": 836.23,
        "416101240": 909.52,
        "516101100": 81.28,
        "516101110": 79.2,
        "516101120": 133.86,
        "516101130": 135.87,
        "516101140": 150.87,
        "516101150": 153.66,
        "516101160": 155.51,
        "516101170": 152.92,
        "516101180": 163.61,
        "516101190": 168.5,
        "516101200": 194.9,
        "516101210": 208.6,
        "516101220": 237.85,
        "516101230": 222.31,
        "516101240": 195.88,
        "616101100": -38.21,
        "616101110": 670.95,
        "616101120": 666.84,
        "616101130": 763.19,
        "616101140": 875.59,
        "616101150": 897.71,
        "616101160": 909.78,
        "616101170": -142.68,
        "616101180": -142.15,
        "616101190": -99.53,
        "616101200": -38.69,
        "616101210": -54.77,
        "616101220": -61.16,
        "616101230": -64.85,
        "616101240": 23.42,
        "716101100": 1887.72,
        "716101110": 2073.1,
        "716101120": 2285.89,
        "716101130": 2546.78,
        "716101140": 2838.07,
        "716101150": 3143.84,
        "716101160": 3442.52,
        "716101170": 3751.63,
        "716101180": 4085.2,
        "716101190": 4434.72,
        "716101200": 4542.85,
        "716101210": 4755.23,
        "716101220": 5166.25,
        "716101230": 5655.75,
        "716101240": 6100.41
    },
    "related": {
        "1": {
            "id": "MTY2IzI=",
            "title": "Distribusi Persentase PDRB Atas Dasar Harga Berlaku 2010 Menurut Jenis Pengeluaran di Kabupaten Samosir",
            "tablesource": 2,
            "last_update": "2025-02-28",
            "link": "/2/MTY2IzI=/distribusi-persentase-pdrb-atas-dasar-harga-berlaku-2010-menurut-jenis-pengeluaran-di-kabupaten-samosir.html"
        },
        "2": {
            "id": "MTk0IzI=",
            "title": "PDRB Kabupaten Samosir Atas Dasar Harga Berlaku menurut Pengeluaran Tahun 2018-2022",
            "tablesource": 2,
            "last_update": "2023-02-28",
            "link": "/2/MTk0IzI=/pdrb-kabupaten-samosir-atas-dasar-harga-berlaku-menurut-pengeluaran-tahun-2018-2022.html"
        },
        "3": {
            "id": "MTY0IzI=",
            "title": "PDRB Atas Dasar Harga Konstan 2010 Menurut Jenis Pengeluaran di Kabupaten Samosir",
            "tablesource": 2,
            "last_update": "2025-02-28",
            "link": "/2/MTY0IzI=/pdrb-atas-dasar-harga-konstan-2010-menurut-jenis-pengeluaran-di-kabupaten-samosir.html"
        },
        "4": {
            "id": "MTQ5IzI=",
            "title": "PDRB Atas Dasar Harga Berlaku Menurut Lapangan Usaha di Kabupaten Samosir",
            "tablesource": 2,
            "last_update": "2025-02-27",
            "link": "/2/MTQ5IzI=/pdrb-atas-dasar-harga-berlaku-menurut-lapangan-usaha-di-kabupaten-samosir.html"
        },
        "5": {
            "id": "MTkyIzI=",
            "title": "Pertumbuhan PDRB Kabupaten Samosir Atas Dasar Harga Konstan 2010 Menurut Pengeluaran",
            "tablesource": 2,
            "last_update": null,
            "link": "/2/MTkyIzI=/pertumbuhan-pdrb-kabupaten-samosir-atas-dasar-harga-konstan-2010-menurut-pengeluaran.html"
        },
        "6": {
            "id": "MTUyIzI=",
            "title": "Distribusi Persentase PDRB Atas Dasar Harga Berlaku Menurut Lapangan Usaha di Kabupaten Samosir",
            "tablesource": 2,
            "last_update": "2025-02-27",
            "link": "/2/MTUyIzI=/distribusi-persentase-pdrb-atas-dasar-harga-berlaku-menurut-lapangan-usaha-di-kabupaten-samosir.html"
        },
        "7": {
            "id": "MTkwIzI=",
            "title": "Produk Domestik Regional Bruto Kabupaten Samosir Atas Dasar Harga Berlaku menurut pengeluaran ",
            "tablesource": 2,
            "last_update": "2024-03-13",
            "link": "/2/MTkwIzI=/produk-domestik-regional-bruto-kabupaten-samosir-atas-dasar-harga-berlaku-menurut-pengeluaran-.html"
        }
    }
}