{
    "status": "OK",
    "data-availability": "available",
    "last_update": "2025-02-28 12:35:43",
    "subject": [
        {
            "val": 531,
            "label": "Neraca Ekonomi"
        }
    ],
    "var": [
        {
            "val": 166,
            "label": "Distribusi Persentase PDRB Atas Dasar Harga Berlaku 2010 Menurut Jenis Pengeluaran di Kabupaten Samosir",
            "unit": "Persen",
            "subj": "Produk Domestik Regional Bruto Menurut Pengeluaran",
            "def": "PDRB adalah semua komponen permintaan akhir yang terdiri dari: (1) pengeluaran konsumsi akhir rumah tangga (2) pengeluaran konsumsi akhir lembaga non profit yang melayani rumah tangga (3) pengeluaran konsumsi akhir pemerintah, (4) pembentukan modal tetap domestik bruto, (5) perubahan inventori, dan (6) ekspor neto (ekspor dikurangi impor).\nDistribusi PDRB harga berlaku menurut sektor menunjukkan struktur perekonomian atau peranan setiap sektor ekonomi dalam suatu wilayah regional. Sektor-sektor ekonomi yang mempunyai peran besar menunjukkan basis perekonomian suatu wilayah regional.",
            "decimal": 2,
            "note": "* Angka Sementara (2023) ** Angka Sangat Sementara (2024)"
        }
    ],
    "turvar": [
        {
            "val": "0",
            "label": "Tidak ada"
        }
    ],
    "labelvervar": "Komponen PDRB Pengeluaran",
    "vervar": [
        {
            "val": 1,
            "label": "1. Pengeluaran Konsumsi Rumahtangga"
        },
        {
            "val": 2,
            "label": "2. Pengeluaran Konsumsi LNPRT"
        },
        {
            "val": 3,
            "label": "3. Pengeluaran Konsumsi Pemerintah"
        },
        {
            "val": 4,
            "label": "4. Pembentukan Modal Tetap Bruto"
        },
        {
            "val": 5,
            "label": "5. Perubahan Inventori"
        },
        {
            "val": 6,
            "label": "6. Net Ekspor Barang dan Jasa"
        },
        {
            "val": 7,
            "label": "PRODUK DOMESTIK REGIONAL BRUTO"
        }
    ],
    "tahun": [
        {
            "val": 110,
            "label": "2010"
        },
        {
            "val": 111,
            "label": "2011"
        },
        {
            "val": 112,
            "label": "2012"
        },
        {
            "val": 113,
            "label": "2013"
        },
        {
            "val": 114,
            "label": "2014"
        },
        {
            "val": 115,
            "label": "2015"
        },
        {
            "val": 116,
            "label": "2016"
        },
        {
            "val": 117,
            "label": "2017"
        },
        {
            "val": 118,
            "label": "2018"
        },
        {
            "val": 119,
            "label": "2019"
        },
        {
            "val": 120,
            "label": "2020"
        },
        {
            "val": 121,
            "label": "2021"
        },
        {
            "val": 122,
            "label": "2022"
        },
        {
            "val": 123,
            "label": "2023"
        },
        {
            "val": 124,
            "label": "2024"
        }
    ],
    "turtahun": [
        {
            "val": 0,
            "label": "Tahun"
        }
    ],
    "datacontent": {
        "116601100": 56.33,
        "116601110": 57.07,
        "116601120": 57.31,
        "116601130": 57.49,
        "116601140": 57.79,
        "116601150": 58.94,
        "116601160": 59.21,
        "116601170": 59.64,
        "116601180": 59.43,
        "116601190": 59.8,
        "116601200": 58.75,
        "116601210": 58.74,
        "116601220": 59.93,
        "116601230": 61.2,
        "116601240": 60.97,
        "216601100": 2.29,
        "216601110": 2.34,
        "216601120": 2.29,
        "216601130": 2.29,
        "216601140": 2.34,
        "216601150": 2.3,
        "216601160": 2.3,
        "216601170": 2.24,
        "216601180": 2.29,
        "216601190": 2.36,
        "216601200": 2.4,
        "216601210": 2.37,
        "216601220": 2.36,
        "216601230": 2.37,
        "216601240": 2.46,
        "316601100": 24.27,
        "316601110": 25.58,
        "316601120": 25.4,
        "316601130": 24.33,
        "316601140": 24.03,
        "316601150": 24.2,
        "316601160": 23.47,
        "316601170": 23.48,
        "316601180": 23.26,
        "316601190": 21.97,
        "316601200": 21.54,
        "316601210": 21.26,
        "316601220": 19.77,
        "316601230": 18.86,
        "316601240": 18.07,
        "416601100": 14.83,
        "416601110": 14.66,
        "416601120": 14.9,
        "416601130": 15.26,
        "416601140": 15.93,
        "416601150": 15.24,
        "416601160": 14.7,
        "416601170": 14.38,
        "416601180": 14.49,
        "416601190": 14.32,
        "416601200": 13.88,
        "416601210": 14.39,
        "416601220": 14.52,
        "416601230": 14.79,
        "416601240": 14.91,
        "516601100": 4.31,
        "516601110": 3.82,
        "516601120": 5.86,
        "516601130": 5.34,
        "516601140": 5.32,
        "516601150": 4.89,
        "516601160": 4.52,
        "516601170": 4.08,
        "516601180": 4,
        "516601190": 3.8,
        "516601200": 4.29,
        "516601210": 4.39,
        "516601220": 4.6,
        "516601230": 3.93,
        "516601240": 3.21,
        "616601100": -2.02,
        "616601110": -3.47,
        "616601120": -5.76,
        "616601130": -4.71,
        "616601140": -5.41,
        "616601150": -5.57,
        "616601160": -4.19,
        "616601170": -3.8,
        "616601180": -3.48,
        "616601190": -2.24,
        "616601200": -0.85,
        "616601210": -1.15,
        "616601220": -1.18,
        "616601230": -1.15,
        "616601240": 0.38,
        "716601100": 100,
        "716601110": 100,
        "716601120": 100,
        "716601130": 100,
        "716601140": 100,
        "716601150": 100,
        "716601160": 100,
        "716601170": 100,
        "716601180": 100,
        "716601190": 100,
        "716601200": 100,
        "716601210": 100,
        "716601220": 100,
        "716601230": 100,
        "716601240": 100
    },
    "related": {
        "1": {
            "id": "MTUyIzI=",
            "title": "Distribusi Persentase PDRB Atas Dasar Harga Berlaku Menurut Lapangan Usaha di Kabupaten Samosir",
            "tablesource": 2,
            "last_update": "2025-02-27",
            "link": "/2/MTUyIzI=/distribusi-persentase-pdrb-atas-dasar-harga-berlaku-menurut-lapangan-usaha-di-kabupaten-samosir.html"
        },
        "2": {
            "id": "MTYxIzI=",
            "title": "PDRB Atas Dasar Harga Berlaku Menurut Jenis Pengeluaran di Kabupaten Samosir",
            "tablesource": 2,
            "last_update": "2025-02-27",
            "link": "/2/MTYxIzI=/pdrb-atas-dasar-harga-berlaku-menurut-jenis-pengeluaran-di-kabupaten-samosir.html"
        },
        "3": {
            "id": "MTkyIzI=",
            "title": "Pertumbuhan PDRB Kabupaten Samosir Atas Dasar Harga Konstan 2010 Menurut Pengeluaran",
            "tablesource": 2,
            "last_update": null,
            "link": "/2/MTkyIzI=/pertumbuhan-pdrb-kabupaten-samosir-atas-dasar-harga-konstan-2010-menurut-pengeluaran.html"
        },
        "4": {
            "id": "MTk0IzI=",
            "title": "PDRB Kabupaten Samosir Atas Dasar Harga Berlaku menurut Pengeluaran Tahun 2018-2022",
            "tablesource": 2,
            "last_update": "2023-02-28",
            "link": "/2/MTk0IzI=/pdrb-kabupaten-samosir-atas-dasar-harga-berlaku-menurut-pengeluaran-tahun-2018-2022.html"
        },
        "5": {
            "id": "MjIwIzI=",
            "title": "[Triwulanan] Distribusi PDRB Atas Dasar Harga Berlaku Menurut Pengeluaran",
            "tablesource": 2,
            "last_update": "2025-03-26",
            "link": "/2/MjIwIzI=/-triwulanan--distribusi-pdrb-atas-dasar-harga-berlaku-menurut-pengeluaran.html"
        },
        "6": {
            "id": "MTY0IzI=",
            "title": "PDRB Atas Dasar Harga Konstan 2010 Menurut Jenis Pengeluaran di Kabupaten Samosir",
            "tablesource": 2,
            "last_update": "2025-02-28",
            "link": "/2/MTY0IzI=/pdrb-atas-dasar-harga-konstan-2010-menurut-jenis-pengeluaran-di-kabupaten-samosir.html"
        },
        "7": {
            "id": "MTY1IzI=",
            "title": "Laju Pertumbuhan PDRB Kabupaten Samosir Atas Dasar Harga Konstan 2010 menurut Pengeluaran",
            "tablesource": 2,
            "last_update": "2025-02-28",
            "link": "/2/MTY1IzI=/laju-pertumbuhan-pdrb-kabupaten-samosir-atas-dasar-harga-konstan-2010-menurut-pengeluaran.html"
        }
    }
}